graia/template/__init__.py
graia_template-0.0.4.dist-info/WHEEL
graia_template-0.0.4.dist-info/METADATA
graia_template-0.0.4.dist-info/RECORD
