Metadata-Version: 2.1
Name: graia-template
Version: 0.0.4
Summary: 
License: MIT
Author: GreyElaina
Author-email: GreyElaina@outlook.com
Requires-Python: >=3.6,<4.0
Classifier: License :: OSI Approved :: MIT License
Classifier: Programming Language :: Python :: 3
Classifier: Programming Language :: Python :: 3.6
Classifier: Programming Language :: Python :: 3.7
Classifier: Programming Language :: Python :: 3.8
Requires-Dist: graia-application-mirai
Requires-Dist: regex (>=2020.7.14,<2021.0.0)
